tixte/__init__.py
tixte/client.py
tixte/config.py
tixte/domain.py
tixte/errors.py
tixte/file.py
tixte/http.py
tixte/user.py
tixte/utils.py
tixte-0.0.6.dist-info/LICENSE
tixte-0.0.6.dist-info/METADATA
tixte-0.0.6.dist-info/WHEEL
tixte-0.0.6.dist-info/entry_points.txt
tixte-0.0.6.dist-info/top_level.txt
tixte-0.0.6.dist-info/RECORD
